{
  "recent_likes": [
    {
      "title": "Scott Pilgrim vs. the World",
      "year": 2010,
      "poster": "https://image.tmdb.org/t/p/w342/g5IoYeudx9XBEfwNL0fHvSckLBz.jpg"
    },
    {
      "title": "Moneyball",
      "year": 2011,
      "poster": "https://image.tmdb.org/t/p/w342/4yIQq1e6iOcaZ5rLDG3lZBP3j7a.jpg"
    },
    {
      "title": "Boogie Nights",
      "year": 1997,
      "poster": "https://image.tmdb.org/t/p/w342/wnE24UPCPQsQnbBOu4zVE2qaDNm.jpg"
    },
    {
      "title": "The Irishman",
      "year": 2019,
      "poster": "https://image.tmdb.org/t/p/w342/mbm8k3GFhXS0ROd9AD1gqYbIFbM.jpg"
    },
    {
      "title": "Chronicle",
      "year": 2012,
      "poster": "https://image.tmdb.org/t/p/w342/kdyrdFIt29FUmLIKvedAc2j4rpo.jpg"
    },
    {
      "title": "Orphan",
      "year": 2009,
      "poster": "https://image.tmdb.org/t/p/w342/lCGpOgoTOGLtZnBiGY9HRg5Xnjd.jpg"
    },
    {
      "title": "Curse of Chucky",
      "year": 2013,
      "poster": "https://image.tmdb.org/t/p/w342/x9DzkDWp8O82Wzxk6otuD9bce9a.jpg"
    },
    {
      "title": "It Follows",
      "year": 2014,
      "poster": "https://image.tmdb.org/t/p/w342/iwnQ1JH1wdWrGYkgWySptJ5284A.jpg"
    }
  ],
  "random_five_stars": [
    {
      "title": "Fallen Angels",
      "year": 1995,
      "poster": "https://image.tmdb.org/t/p/w342/yyM9BPdwttK5LKZSLvHae7QPKo1.jpg"
    },
    {
      "title": "Cars",
      "year": 2006,
      "poster": "https://image.tmdb.org/t/p/w342/2Touk3m5gzsqr1VsvxypdyHY5ci.jpg"
    },
    {
      "title": "John Wick: Chapter 3 – Parabellum",
      "year": 2019,
      "poster": "https://image.tmdb.org/t/p/w342/ziEuG1essDuWuC5lpWUaw1uXY2O.jpg"
    },
    {
      "title": "Spider-Man: Across the Spider-Verse",
      "year": 2023,
      "poster": "https://image.tmdb.org/t/p/w342/8Vt6mWEReuy4Of61Lnj5Xj704m8.jpg"
    },
    {
      "title": "Velaiyilla Pattathari",
      "year": 2014,
      "poster": "https://image.tmdb.org/t/p/w342/fQ8JzXRf68xlzyquLn7TEe3S2Nh.jpg"
    },
    {
      "title": "Get Out",
      "year": 2017,
      "poster": "https://image.tmdb.org/t/p/w342/mE24wUCfjK8AoBBjaMjho7Rczr7.jpg"
    },
    {
      "title": "The Social Network",
      "year": 2010,
      "poster": "https://image.tmdb.org/t/p/w342/n0ybibhJtQ5icDqTp8eRytcIHJx.jpg"
    },
    {
      "title": "Hereditary",
      "year": 2018,
      "poster": "https://image.tmdb.org/t/p/w342/hjlZSXM86wJrfCv5VKfR5DI2VeU.jpg"
    }
  ]
}